tg_auth/__init__.py
tg_auth/backend.py
tg_auth/models.py
tg_auth/router.py
xtg_auth-0.0.19.dist-info/METADATA
xtg_auth-0.0.19.dist-info/WHEEL
xtg_auth-0.0.19.dist-info/top_level.txt
xtg_auth-0.0.19.dist-info/RECORD
