Metadata-Version: 2.4
Name: xtg-auth
Version: 0.0.19
Summary: Authentication backend for Telegram Mini Apps on starlette/fastapi API
Author-email: Artemiev <mixartemev@gmail.com>
License: MIT
Project-URL: Homepage, https://github.com/XyncNet/tg-auth
Project-URL: Repository, https://github.com/XyncNet/tg-auth
Keywords: starlette,fastapi,telegram,authentication,backend,auth
Requires-Python: >=3.11
Requires-Dist: aiogram
Requires-Dist: xn-auth
Provides-Extra: dev
Requires-Dist: build; extra == "dev"
Requires-Dist: python-dotenv; extra == "dev"
Requires-Dist: twine; extra == "dev"
